[
  { "id": "20", "code": "EG", "name": "مصر" },
  { "id": "212", "code": "MA", "name": "المغرب" },
  { "id": "213", "code": "DZ", "name": "الجزائر" },
  { "id": "216", "code": "TN", "name": "تونس" },
  { "id": "218", "code": "LY", "name": "ليبيا" },
  { "id": "222", "code": "MR", "name": "موريتانيا" },
  { "id": "249", "code": "SD", "name": "السودان" },
  { "id": "252", "code": "SO", "name": "الصومال" },
  { "id": "253", "code": "DJ", "name": "جيبوتي" },
  { "id": "269", "code": "KM", "name": "جزر القمر" },
  { "id": "961", "code": "LB", "name": "لبنان" },
  { "id": "962", "code": "JO", "name": "الأردن" },
  { "id": "963", "code": "SR", "name": "سوريا" },
  { "id": "964", "code": "IQ", "name": "العراق" },
  { "id": "965", "code": "KW", "name": "الكويت" },
  { "id": "966", "code": "SA", "name": "السعودية" },
  { "id": "967", "code": "YE", "name": "اليمن" },
  { "id": "968", "code": "OM", "name": "عمان" },
  { "id": "970", "code": "PS", "name": "فلسطين" },
  { "id": "971", "code": "AE", "name": "الإمارات العربية المتحدة" },
  { "id": "973", "code": "BH", "name": "البحرين" },
  { "id": "974", "code": "QA", "name": "قطر" }
]
